ownphotos_client/__init__.py
ownphotos_client/ownphotos_client.py
ownphotos_client-0.1.1.dist-info/LICENSE
ownphotos_client-0.1.1.dist-info/METADATA
ownphotos_client-0.1.1.dist-info/WHEEL
ownphotos_client-0.1.1.dist-info/entry_points.txt
ownphotos_client-0.1.1.dist-info/top_level.txt
ownphotos_client-0.1.1.dist-info/RECORD
