Metadata-Version: 2.1
Name: ownphotos-client
Version: 0.1.1
Summary: Ownphotos client
Home-page: http://github.com/guysoft/ownphotos-client
Author: Guy Sheffer
Author-email: guysoft@gmail.com
License: GPLv3
Keywords: ownphotos
Platform: UNKNOWN
Classifier: Development Status :: 3 - Alpha
Classifier: License :: OSI Approved :: GNU General Public License v3 (GPLv3)
Classifier: Programming Language :: Python :: 3.6
Classifier: Topic :: Text Processing :: Linguistic
Requires-Dist: requests (>=2.21.0)
